DeepmindQianghuaXuexiZhongwenJiangyi/README.md
DeepmindQianghuaXuexiZhongwenJiangyi/__init__.py
DeepmindQianghuaXuexiZhongwenJiangyi/__main__.py
DeepmindQianghuaXuexiZhongwenJiangyi/file.epub
DeepmindQianghuaXuexiZhongwenJiangyi/index.html
DeepmindQianghuaXuexiZhongwenJiangyi/css/__init__.py
DeepmindQianghuaXuexiZhongwenJiangyi/css/annotations.css
DeepmindQianghuaXuexiZhongwenJiangyi/css/main.css
DeepmindQianghuaXuexiZhongwenJiangyi/css/normalize.css
DeepmindQianghuaXuexiZhongwenJiangyi/css/popup.css
DeepmindQianghuaXuexiZhongwenJiangyi/font/__init__.py
DeepmindQianghuaXuexiZhongwenJiangyi/font/fontello.eot
DeepmindQianghuaXuexiZhongwenJiangyi/font/fontello.svg
DeepmindQianghuaXuexiZhongwenJiangyi/font/fontello.ttf
DeepmindQianghuaXuexiZhongwenJiangyi/font/fontello.woff
DeepmindQianghuaXuexiZhongwenJiangyi/img/__init__.py
DeepmindQianghuaXuexiZhongwenJiangyi/img/annotator-glyph-sprite.png
DeepmindQianghuaXuexiZhongwenJiangyi/img/annotator-icon-sprite.png
DeepmindQianghuaXuexiZhongwenJiangyi/img/apple-touch-icon.png
DeepmindQianghuaXuexiZhongwenJiangyi/img/cancelfullscreen.png
DeepmindQianghuaXuexiZhongwenJiangyi/img/close.png
DeepmindQianghuaXuexiZhongwenJiangyi/img/fullscreen.png
DeepmindQianghuaXuexiZhongwenJiangyi/img/loader.gif
DeepmindQianghuaXuexiZhongwenJiangyi/img/menu-icon.png
DeepmindQianghuaXuexiZhongwenJiangyi/img/save.png
DeepmindQianghuaXuexiZhongwenJiangyi/img/saved.png
DeepmindQianghuaXuexiZhongwenJiangyi/img/settings-s.png
DeepmindQianghuaXuexiZhongwenJiangyi/img/settings.png
DeepmindQianghuaXuexiZhongwenJiangyi/img/star.png
DeepmindQianghuaXuexiZhongwenJiangyi/js/__init__.py
DeepmindQianghuaXuexiZhongwenJiangyi/js/epub.js
DeepmindQianghuaXuexiZhongwenJiangyi/js/epub.min.js
DeepmindQianghuaXuexiZhongwenJiangyi/js/epub.min.map
DeepmindQianghuaXuexiZhongwenJiangyi/js/hooks.min.js
DeepmindQianghuaXuexiZhongwenJiangyi/js/hooks.min.map
DeepmindQianghuaXuexiZhongwenJiangyi/js/reader.js
DeepmindQianghuaXuexiZhongwenJiangyi/js/reader.js.map
deepmind_qianghua_xuexi_zhongwen_jiangyi-2024.3.4.0.dist-info/METADATA
deepmind_qianghua_xuexi_zhongwen_jiangyi-2024.3.4.0.dist-info/WHEEL
deepmind_qianghua_xuexi_zhongwen_jiangyi-2024.3.4.0.dist-info/entry_points.txt
deepmind_qianghua_xuexi_zhongwen_jiangyi-2024.3.4.0.dist-info/top_level.txt
deepmind_qianghua_xuexi_zhongwen_jiangyi-2024.3.4.0.dist-info/RECORD
